fentik/__init__.py
fentik/auth.py
fentik/deploy.py
fentik/list.py
fentik/main.py
fentik/util.py
fentik-0.0.2.data/scripts/fentik
fentik-0.0.2.dist-info/LICENSE
fentik-0.0.2.dist-info/METADATA
fentik-0.0.2.dist-info/WHEEL
fentik-0.0.2.dist-info/top_level.txt
fentik-0.0.2.dist-info/RECORD
