Metadata-Version: 2.1
Name: fentik
Version: 0.0.2
Summary: Real-time data platform for in product experiences
Home-page: https://github.com/fentik/fentik-cli
Author: Fentik, Inc.
Author-email: support@fentik.com
License: UNKNOWN
Platform: UNKNOWN
License-File: LICENSE
Requires-Dist: PrettyTable
Requires-Dist: graphqlclient
Requires-Dist: yaml
